autocoder_nano/__init__.py
autocoder_nano/acmodels.py
autocoder_nano/acrunner.py
autocoder_nano/actypes.py
autocoder_nano/auto_coder_nano.py
autocoder_nano/editor.py
autocoder_nano/helper.py
autocoder_nano/templates.py
autocoder_nano/version.py
autocoder_nano/agent/__init__.py
autocoder_nano/agent/agent_base.py
autocoder_nano/agent/agent_define.py
autocoder_nano/agent/agentic_edit_types.py
autocoder_nano/agent/agentic_runtime.py
autocoder_nano/agent/agentic_skills.py
autocoder_nano/agent/agentic_sub.py
autocoder_nano/agent/agentic_edit_tools/__init__.py
autocoder_nano/agent/agentic_edit_tools/ac_mod_search_tool.py
autocoder_nano/agent/agentic_edit_tools/ac_mod_write_tool.py
autocoder_nano/agent/agentic_edit_tools/ask_followup_question_tool.py
autocoder_nano/agent/agentic_edit_tools/attempt_completion_tool.py
autocoder_nano/agent/agentic_edit_tools/base_tool_resolver.py
autocoder_nano/agent/agentic_edit_tools/call_cusagent_tool.py
autocoder_nano/agent/agentic_edit_tools/call_skills_tool.py
autocoder_nano/agent/agentic_edit_tools/call_subagent_tool.py
autocoder_nano/agent/agentic_edit_tools/execute_command_tool.py
autocoder_nano/agent/agentic_edit_tools/list_files_tool.py
autocoder_nano/agent/agentic_edit_tools/read_file_tool.py
autocoder_nano/agent/agentic_edit_tools/replace_in_file_tool.py
autocoder_nano/agent/agentic_edit_tools/search_files_tool.py
autocoder_nano/agent/agentic_edit_tools/todo_read_tool.py
autocoder_nano/agent/agentic_edit_tools/todo_write_tool.py
autocoder_nano/agent/agentic_edit_tools/use_rag_tool.py
autocoder_nano/agent/agentic_edit_tools/web_reader_tool.py
autocoder_nano/agent/agentic_edit_tools/web_search_tool.py
autocoder_nano/agent/agentic_edit_tools/write_to_file_tool.py
autocoder_nano/agent/prompt/agentic_rag_system_prompt.md
autocoder_nano/agent/prompt/codereview_system_prompt.md
autocoder_nano/agent/prompt/coding_system_prompt.md
autocoder_nano/agent/prompt/main_system_prompt.md
autocoder_nano/agent/prompt/reader_system_prompt.md
autocoder_nano-0.4.12.dist-info/LICENSE
autocoder_nano-0.4.12.dist-info/METADATA
autocoder_nano-0.4.12.dist-info/WHEEL
autocoder_nano-0.4.12.dist-info/entry_points.txt
autocoder_nano-0.4.12.dist-info/top_level.txt
autocoder_nano-0.4.12.dist-info/RECORD
