Metadata-Version: 2.2
Name: autocoder_nano
Version: 0.4.12
Summary: AutoCoder Nano
Author: moofs
Classifier: Topic :: Scientific/Engineering :: Artificial Intelligence
Classifier: Programming Language :: Python :: 3.10
Classifier: Programming Language :: Python :: 3.11
Requires-Python: >=3.10
License-File: LICENSE
Requires-Dist: loguru
Requires-Dist: GitPython
Requires-Dist: jinja2
Requires-Dist: openai>=1.14.3
Requires-Dist: prompt_toolkit
Requires-Dist: pydantic
Requires-Dist: rich
Requires-Dist: pylint
Requires-Dist: PyYAML
Requires-Dist: pdfminer
Requires-Dist: pypdf
Requires-Dist: pathspec
Requires-Dist: tokenizers
Requires-Dist: duckdb
Requires-Dist: numpy
Requires-Dist: psutil
Requires-Dist: cutword
Requires-Dist: pandas
Dynamic: author
Dynamic: classifier
Dynamic: description
Dynamic: description-content-type
Dynamic: requires-dist
Dynamic: requires-python
Dynamic: summary
